py_collector/__init__.py
py_collector/py_collector.py
py_collector-0.0.25.dist-info/LICENSE
py_collector-0.0.25.dist-info/METADATA
py_collector-0.0.25.dist-info/WHEEL
py_collector-0.0.25.dist-info/top_level.txt
py_collector-0.0.25.dist-info/RECORD
