Metadata-Version: 2.1
Name: py_collector
Version: 0.0.25
Summary: A small data collection package for small to medium data collection efforts.
Home-page: https://github.com/Michael-fore/py_collector
Author: Michael Watson-Fore
Author-email: michael-fore@sbcglobal.net
License: UNKNOWN
Project-URL: Bug Tracker, https://github.com/Michael-fore/py_collector/issues
Keywords: dataharvesting,datascraping,scraping,datacollection
Platform: UNKNOWN
Classifier: Programming Language :: Python :: 3
Classifier: License :: OSI Approved :: MIT License
Classifier: Operating System :: OS Independent
Classifier: Development Status :: 3 - Alpha
Classifier: Environment :: Console
Requires-Python: >=3.2
License-File: LICENSE
